hx_mcp_demo/__init__.py
hx_mcp_demo-0.1.0.dist-info/WHEEL
hx_mcp_demo-0.1.0.dist-info/entry_points.txt
hx_mcp_demo-0.1.0.dist-info/METADATA
hx_mcp_demo-0.1.0.dist-info/RECORD
