Metadata-Version: 2.3
Name: hx-mcp-demo
Version: 0.1.0
Summary: Add your description here
Author: 2024103861
Author-email: 2024103861 <2024103861@ruc.edu.cn>
Requires-Dist: mcp[cli]>=1.17.0
Requires-Python: >=3.11
